sgnova/__init__.py
sgnova/_version.py
sgnova/py.typed
sgnova/bin/__init__.py
sgnova/transforms/__init__.py
sgnova/transforms/power.py
sgnova-0.0.1.dist-info/LICENSE
sgnova-0.0.1.dist-info/METADATA
sgnova-0.0.1.dist-info/WHEEL
sgnova-0.0.1.dist-info/top_level.txt
sgnova-0.0.1.dist-info/RECORD
