Metadata-Version: 2.2
Name: sgnova
Version: 0.0.1
Summary: Burst Search Pipeline using SGN Framework
Author-email: James Kennington <jwkennington@psu.edu>
License: MPL-2.0
Project-URL: Homepage, https://git.ligo.org/greg/sgnova
Project-URL: Documentation, https://greg.docs.ligo.org/sgnova
Project-URL: Issues, https://git.ligo.org/greg/sgnova/issues
Classifier: Programming Language :: Python :: 3
Classifier: License :: OSI Approved :: Mozilla Public License 2.0 (MPL 2.0)
Classifier: Operating System :: OS Independent
Requires-Python: >=3.9
License-File: LICENSE
Requires-Dist: sgn
Requires-Dist: sgn-ts
Requires-Dist: sgn-ligo
Provides-Extra: visualize
Requires-Dist: graphviz; extra == "visualize"
Provides-Extra: test
Requires-Dist: sgnova[visualize]; extra == "test"
Requires-Dist: numpy; extra == "test"
Requires-Dist: pytest; extra == "test"
Requires-Dist: pytest-cov; extra == "test"
Requires-Dist: pytest-markdown-docs; extra == "test"
Provides-Extra: docs
Requires-Dist: mkdocs; extra == "docs"
Requires-Dist: mkdocstrings; extra == "docs"
Requires-Dist: mkdocstrings-python; extra == "docs"
Requires-Dist: mkdocs-material; extra == "docs"
Requires-Dist: pymdown-extensions; extra == "docs"
Provides-Extra: lint
Requires-Dist: black; extra == "lint"
Requires-Dist: flake8; extra == "lint"
Requires-Dist: flake8-bandit; extra == "lint"
Requires-Dist: flake8-black; extra == "lint"
Requires-Dist: flake8-bugbear; extra == "lint"
Requires-Dist: flake8-future-annotations; extra == "lint"
Requires-Dist: flake8-isort; extra == "lint"
Requires-Dist: flake8-logging-format; extra == "lint"
Requires-Dist: flake8-pyproject; extra == "lint"
Requires-Dist: isort; extra == "lint"
Requires-Dist: mypy; extra == "lint"
Requires-Dist: mypy-extensions; extra == "lint"
Provides-Extra: dev
Requires-Dist: sgnova[docs]; extra == "dev"
Requires-Dist: sgnova[lint]; extra == "dev"
Requires-Dist: sgnova[test]; extra == "dev"
